NAGATO/IxNetworkLibrary/__init__.py
NAGATO/IxNetworkLibrary/_wrapper.py
NAGATO/NetmikoLibrary/README.md
NAGATO/NetmikoLibrary/__init__.py
NAGATO/NetmikoLibrary/_wrapper.py
NAGATO/NetmikoLibrary/apresia/__init__.py
NAGATO/NetmikoLibrary/apresia/apresia_amios.py
NAGATO/NetmikoLibrary/set_templates.py
NAGATO/PcapFileReader.py
NAGATO/Resources/Cisco_IOS_XR.resource
NAGATO/Resources/Juniper_Junos.resource
NAGATO/Resources/README.md
NAGATO/SNMP.py
NAGATO/__init__.py
NAGATO/templates/apresia_amios_show_status_card.textfsm
NAGATO/templates/cisco_xr_show_access-lists.textfsm
NAGATO/templates/cisco_xr_show_access-lists_interface.textfsm
NAGATO/templates/cisco_xr_show_arm_router-ids.textfsm
NAGATO/templates/cisco_xr_show_bfd_ipv4.textfsm
NAGATO/templates/cisco_xr_show_bfd_ipv4_session.textfsm
NAGATO/templates/cisco_xr_show_bfd_ipv4_session_detail.textfsm
NAGATO/templates/cisco_xr_show_bfd_ipv6.textfsm
NAGATO/templates/cisco_xr_show_bfd_ipv6_session.textfsm
NAGATO/templates/cisco_xr_show_bgp_ipv4_unicast.textfsm
NAGATO/templates/cisco_xr_show_bgp_ipv4_unicast_advertised_neighbor.textfsm
NAGATO/templates/cisco_xr_show_bgp_ipv4_unicast_neighbors.textfsm
NAGATO/templates/cisco_xr_show_bgp_ipv4_unicast_network.textfsm
NAGATO/templates/cisco_xr_show_bgp_ipv6_unicast.textfsm
NAGATO/templates/cisco_xr_show_bgp_ipv6_unicast_advertised_neighbor.textfsm
NAGATO/templates/cisco_xr_show_bgp_ipv6_unicast_neighbors.textfsm
NAGATO/templates/cisco_xr_show_bgp_ipv6_unicast_neighbors_brief.textfsm
NAGATO/templates/cisco_xr_show_bgp_ipv6_unicast_network.textfsm
NAGATO/templates/cisco_xr_show_bgp_neighbors_brief.textfsm
NAGATO/templates/cisco_xr_show_bgp_sessions.textfsm
NAGATO/templates/cisco_xr_show_bgp_vrf_all_ipv6_unicast_summary.textfsm
NAGATO/templates/cisco_xr_show_bundle_bundle-ether.textfsm
NAGATO/templates/cisco_xr_show_ethernet_oam_event-log.textfsm
NAGATO/templates/cisco_xr_show_interfaces_brief.textfsm
NAGATO/templates/cisco_xr_show_ipv6_interface.textfsm
nagato_network-1.0.0.dist-info/LICENSE
nagato_network-1.0.0.dist-info/METADATA
nagato_network-1.0.0.dist-info/WHEEL
nagato_network-1.0.0.dist-info/RECORD
