Metadata-Version: 2.1
Name: nagato-network
Version: 1.0.0
Summary: NAGATO: Network Automation Gears and Test Orchestrator
Home-page: https://github.com/ctc-nt/NAGATO
License: Apache-2.0
Author: Takumi Nohara
Requires-Python: >=3.8,<4.0
Classifier: Framework :: Robot Framework
Classifier: License :: OSI Approved :: Apache Software License
Classifier: Operating System :: OS Independent
Classifier: Programming Language :: Python :: 3
Classifier: Programming Language :: Python :: 3.8
Classifier: Programming Language :: Python :: 3.9
Classifier: Programming Language :: Python :: 3.10
Classifier: Programming Language :: Python :: 3.11
Classifier: Programming Language :: Python :: 3.12
Requires-Dist: ixnetwork-restpy (>=1.1.10)
Requires-Dist: netmiko (>=4.0.0)
Requires-Dist: ntc-templates (>=3.5.0)
Requires-Dist: pyshark (>=0.6)
Requires-Dist: pysnmp (>=6.2.4,<7.0.0)
Requires-Dist: robotframework (>=5.0.0)
Requires-Dist: setuptools (>=70.0.0,<71.0.0)
Project-URL: Repository, https://github.com/ctc-nt/NAGATO
